npyetl/__init__.py
npyetl/collab/__init__.py
npyetl/collab/azure_/__init__.py
npyetl/collab/azure_/extractors.py
npyetl/collab/azure_/loaders.py
npyetl/collab/csv_/__init__.py
npyetl/collab/csv_/extractors.py
npyetl/collab/csv_/loaders.py
npyetl/collab/gmail_/__init__.py
npyetl/collab/gmail_/extractors.py
npyetl/collab/gmail_/gmail/__init__.py
npyetl/collab/gmail_/gmail/api/__init__.py
npyetl/collab/gmail_/gmail/api/api.py
npyetl/collab/gmail_/gmail/objects/__init__.py
npyetl/collab/gmail_/gmail/objects/_base_object.py
npyetl/collab/gmail_/gmail/objects/draft.py
npyetl/collab/gmail_/gmail/objects/history.py
npyetl/collab/gmail_/gmail/objects/label.py
npyetl/collab/gmail_/gmail/objects/thread.py
npyetl/collab/gmail_/gmail/objects/message/__init__.py
npyetl/collab/gmail_/gmail/objects/message/_base_message.py
npyetl/collab/gmail_/gmail/objects/message/attachment.py
npyetl/collab/gmail_/gmail/objects/message/message.py
npyetl/collab/json_/__init__.py
npyetl/collab/json_/extractors.py
npyetl/collab/json_/loaders.py
npyetl/collab/sql/__init__.py
npyetl/collab/sql/extractors.py
npyetl/data/__init__.py
npyetl/data/dask_data_block.py
npyetl/data/data_block.py
npyetl/data/pandas_data_block.py
npyetl/extraction/__init__.py
npyetl/extraction/extractor.py
npyetl/internals/__init__.py
npyetl/internals/decorators/__init__.py
npyetl/internals/decorators/override_method.py
npyetl/load/__init__.py
npyetl/load/loader.py
npyetl/pipeline/__init__.py
npyetl/pipeline/logger.py
npyetl/pipeline/logger_loader.py
npyetl/pipeline/pipeline.py
npyetl/transformation/__init__.py
npyetl/transformation/transformer.py
pyetl/__init__.py
pyetl/collab/__init__.py
pyetl/collab/azure_/__init__.py
pyetl/collab/azure_/extractors.py
pyetl/collab/azure_/loaders.py
pyetl/collab/csv_/__init__.py
pyetl/collab/csv_/extractors.py
pyetl/collab/csv_/loaders.py
pyetl/collab/gmail_/__init__.py
pyetl/collab/gmail_/extractors.py
pyetl/collab/gmail_/gmail/__init__.py
pyetl/collab/gmail_/gmail/api/__init__.py
npyetl-0.0.5.dist-info/LICENSE
npyetl-0.0.5.dist-info/METADATA
npyetl-0.0.5.dist-info/WHEEL
npyetl-0.0.5.dist-info/top_level.txt
npyetl-0.0.5.dist-info/RECORD
