Metadata-Version: 2.1
Name: npyetl
Version: 0.0.5
Summary: UNKNOWN
Home-page: UNKNOWN
Author: Miquel Escobar
Author-email: mec@novicell.es
License: MIT License
Requires-Dist: pandas
Requires-Dist: dask
Requires-Dist: azure-common
Requires-Dist: azure-core
Requires-Dist: azure-cosmosdb-table
Requires-Dist: azure-storage-file
Requires-Dist: azure-storage-queue (==2.1.0)
Requires-Dist: azure-storage-blob (>=12.0.0)
Requires-Dist: azure-storage-file-datalake
Requires-Dist: google
Requires-Dist: google-api-python-client
Requires-Dist: pyodbc
